mastercard_retail_location_insights-1.0.5.dist-info/DESCRIPTION.rst
mastercard_retail_location_insights-1.0.5.dist-info/METADATA
mastercard_retail_location_insights-1.0.5.dist-info/RECORD
mastercard_retail_location_insights-1.0.5.dist-info/WHEEL
mastercard_retail_location_insights-1.0.5.dist-info/metadata.json
mastercard_retail_location_insights-1.0.5.dist-info/top_level.txt
mastercardretaillocationinsights/__init__.py
mastercardretaillocationinsights/merchantindustries.py
mastercardretaillocationinsights/resourceconfig.py
mastercardretaillocationinsights/retailunitmerchants.py
mastercardretaillocationinsights/retailunits.py
mastercardretaillocationinsights/retailunitsmetrics.py
mastercardretaillocationinsights/subscriptions.py
